Metadata-Version: 1.0
Name: newts
Version: 0.0.1
Summary: Center for NEWTS
Home-page: https://github.com/benmontet/newts
Author: Benjamin Montet
Author-email: b.montet@unsw.edu.au
License: MIT
Platform: UNKNOWN
